ailia/LICENSE_AILIA_EN.pdf
ailia/LICENSE_AILIA_JA.pdf
ailia/__init__.py
ailia/const.py
ailia/core.py
ailia/license.py
ailia/pose_core.py
ailia/wrapper.py
ailia/audio/__init__.py
ailia/audio/core.py
ailia/audio/wrapper.py
ailia/mac/libailia.dylib
ailia/mac/libailia_audio.dylib
ailia/mac/libailia_blas.dylib
ailia/mac/libailia_pose_estimate.dylib
ailia/oss/LICENSE_GLSLANG.txt
ailia/oss/LICENSE_INTELMKL.txt
ailia/oss/LICENSE_VULKAN_HEADERS.txt
ailia-1.6.1.0.data/scripts/__init__.py
ailia-1.6.1.0.data/scripts/const.py
ailia-1.6.1.0.data/scripts/core.py
ailia-1.6.1.0.data/scripts/license.py
ailia-1.6.1.0.data/scripts/pose_core.py
ailia-1.6.1.0.data/scripts/wrapper.py
ailia-1.6.1.0.dist-info/METADATA
ailia-1.6.1.0.dist-info/WHEEL
ailia-1.6.1.0.dist-info/top_level.txt
ailia-1.6.1.0.dist-info/RECORD
