Metadata-Version: 2.4
Name: ailia
Version: 1.6.1.0
Summary: ailia SDK
Home-page: https://ailia.ai/
Author: ailia Inc.
Author-email: contact@ailia.ai
License: https://ailia.ai/license/en/
Requires-Python: >3.6
Dynamic: author
Dynamic: author-email
Dynamic: description
Dynamic: description-content-type
Dynamic: home-page
Dynamic: license
Dynamic: requires-python
Dynamic: summary
